monkey/__init__.py
monkey/ioc/__init__.py
monkey/ioc/core.py
monkey.ioc-1.0.0.dev7.dist-info/LICENSE.txt
monkey.ioc-1.0.0.dev7.dist-info/METADATA
monkey.ioc-1.0.0.dev7.dist-info/WHEEL
monkey.ioc-1.0.0.dev7.dist-info/top_level.txt
monkey.ioc-1.0.0.dev7.dist-info/RECORD
